Metadata-Version: 2.4
Name: SUN-DIC
Version: 0.0.24
Summary: Stellenbosch University Digital Image Correlation Library
Home-page: https://github.com/gventer/SUN-DIC
Author: Gerhard Venter
Author-email: gventer@sun.ac.za
License: MIT License
Platform: any
Classifier: License :: OSI Approved :: MIT License
Classifier: Programming Language :: Python :: 3
Requires-Python: >=3.11
License-File: LICENSE
Requires-Dist: numpy>=2.2.6
Requires-Dist: natsort>=8.4.0
Requires-Dist: opencv_python_headless>=4.12.0.88
Requires-Dist: scikit-image>=0.25.2
Requires-Dist: ray>=2.49.1
Requires-Dist: numba>=0.61.2
Requires-Dist: msgpack-numpy>=0.4.8
Requires-Dist: matplotlib>=3.10.6
Requires-Dist: jupyter>=1.1.1
Requires-Dist: pandas>=2.3.2
Requires-Dist: PyQT6>=6.9
Dynamic: author
Dynamic: author-email
Dynamic: classifier
Dynamic: description
Dynamic: description-content-type
Dynamic: home-page
Dynamic: license
Dynamic: license-file
Dynamic: platform
Dynamic: requires-dist
Dynamic: requires-python
Dynamic: summary
